eraXplor_aws/__main__.py
eraXplor_aws/utils/__init__.py
eraXplor_aws/utils/banner_utils.py
eraXplor_aws/utils/cost_export_utils.py
eraXplor_aws/utils/csv_export_utils.py
eraXplor_aws/utils/date_utils.py
eraXplor_aws/utils/parser_utils.py
eraXplor_azure/__main__.py
eraXplor_azure/utils/__init__.py
eraXplor_azure/utils/banner_utils.py
eraXplor_azure/utils/cost_export_utils.py
eraXplor_azure/utils/csv_export_utils.py
eraXplor_azure/utils/parser_utils.py
eraxplor-3.2.0.dist-info/METADATA
eraxplor-3.2.0.dist-info/WHEEL
eraxplor-3.2.0.dist-info/entry_points.txt
eraxplor-3.2.0.dist-info/top_level.txt
eraxplor-3.2.0.dist-info/RECORD
