Metadata-Version: 2.4
Name: eraXplor
Version: 3.2.0
Summary: A Python CLI tool for exporting cost reports over Multi-providers AWS/Azure.
Author-email: Mohamed eraki <mohamed-ibrahim2021@outlook.com>
License: Apache-2.0
Project-URL: Repository, https://github.com/Mohamed-Eleraki/eraXplor.git
Project-URL: Issues, https://github.com/Mohamed-Eleraki/eraXplor/issues
Keywords: CLI,ASCII Art
Classifier: Development Status :: 3 - Alpha
Classifier: Intended Audience :: Developers
Classifier: License :: OSI Approved :: Apache Software License
Classifier: Programming Language :: Python :: 3.12
Classifier: Programming Language :: Python :: 3
Classifier: Topic :: System :: Systems Administration
Classifier: Intended Audience :: System Administrators
Classifier: Intended Audience :: Information Technology
Classifier: Topic :: Software Development :: Libraries :: Python Modules
Classifier: Topic :: Software Development :: Libraries :: Application Frameworks
Classifier: Topic :: Software Development :: Libraries :: Python Modules
Classifier: Environment :: Console
Requires-Python: >=3.12.3
Requires-Dist: boto3>=1.37.0
Requires-Dist: pyfiglet>=1.0.2
Requires-Dist: python-dateutil>=2.9.0
Requires-Dist: termcolor>=3.0.1
Requires-Dist: rich>=13.7.1
Requires-Dist: azure.identity>=1.23.0
Requires-Dist: azure.mgmt.costmanagement>=4.0.1
Provides-Extra: dev
Requires-Dist: pytest>=8.0.0; extra == "dev"
Requires-Dist: pytest-mock>=3.14.0; extra == "dev"
Requires-Dist: pytest-cov>=4.1.0; extra == "dev"
Requires-Dist: mkdocs>=1.6.1; extra == "dev"
Requires-Dist: mkdocs-autorefs>=1.4.1; extra == "dev"
Requires-Dist: mkdocs-get-deps>=0.2.0; extra == "dev"
Requires-Dist: mkdocs-material>=9.6.12; extra == "dev"
Requires-Dist: mkdocs-material-extensions>=1.3.1; extra == "dev"
Requires-Dist: mkdocs-mermaid2-plugin>=1.2.1; extra == "dev"
Requires-Dist: mkdocstrings>=0.29.1; extra == "dev"
Requires-Dist: mkdocstrings-python>=1.16.10; extra == "dev"
Requires-Dist: pylint>=3.3.6; extra == "dev"
Requires-Dist: isort>=6.0.1; extra == "dev"
